LICENSE
README.md
setup.py
pathtrees/__init__.py
pathtrees/__version__.py
pathtrees/core.py
pathtrees/util.py
pathtrees.egg-info/PKG-INFO
pathtrees.egg-info/SOURCES.txt
pathtrees.egg-info/dependency_links.txt
pathtrees.egg-info/requires.txt
pathtrees.egg-info/top_level.txt