Metadata-Version: 2.1
Name: pathtrees
Version: 0.0.1
Summary: Define named directory structure using placeholders
Home-page: https://github.com/beasteers/pathtrees
Author: Bea Steers
Author-email: bea.steers@gmail.com
License: MIT License
Keywords: path directory tree structure partial format
Platform: UNKNOWN
License-File: LICENSE
